sqlmap_websocket_proxy/__init__.py
sqlmap_websocket_proxy/console.py
sqlmap_websocket_proxy/handler.py
sqlmap_websocket_proxy/main.py
sqlmap_websocket_proxy-1.1.0.dist-info/LICENSE
sqlmap_websocket_proxy-1.1.0.dist-info/METADATA
sqlmap_websocket_proxy-1.1.0.dist-info/WHEEL
sqlmap_websocket_proxy-1.1.0.dist-info/entry_points.txt
sqlmap_websocket_proxy-1.1.0.dist-info/top_level.txt
sqlmap_websocket_proxy-1.1.0.dist-info/RECORD
