Metadata-Version: 2.1
Name: sqlmap-websocket-proxy
Version: 1.1.0
Summary: HTTP Proxy for using sqlmap against websockets
Author-email: Brandon Kreisel <BKreisel@users.noreply.github.com>
Project-URL: Homepage, https://github.com/BKreisel/sqlmap-websocket-proxy
Project-URL: Bug Tracker, https://github.com/BKreisel/sqlmap-websocket-proxy/issues
Classifier: Programming Language :: Python :: 3
Classifier: License :: OSI Approved :: MIT License
Classifier: Operating System :: OS Independent
Requires-Python: >=3.11
License-File: LICENSE
Requires-Dist: websocket-client
Requires-Dist: rich
Provides-Extra: dev
Requires-Dist: ruff ; extra == 'dev'
